excelmanager/__init__.py
excelmanager/excel_manager.py
excelmanager-1.0.1.dist-info/LICENSE.txt
excelmanager-1.0.1.dist-info/METADATA
excelmanager-1.0.1.dist-info/WHEEL
excelmanager-1.0.1.dist-info/top_level.txt
excelmanager-1.0.1.dist-info/RECORD
