Metadata-Version: 2.1
Name: excelmanager
Version: 1.0.1
Summary: A simplified wrapper around `openpyxl` optimized for easy read and write operations.
Author: Erik Bierbrauer
Project-URL: Homepage, https://github.com/ebier92/excelmanager
Project-URL: Bug Tracker, https://github.com/ebier92/excelmanager/issues
Classifier: Programming Language :: Python :: 3
Classifier: License :: OSI Approved :: Apache Software License
Classifier: Operating System :: OS Independent
Requires-Python: >=3.10
License-File: LICENSE.txt
Requires-Dist: openpyxl ==3.1.5
